qpe_fit/__init__.py
qpe_fit/generate_timings.py
qpe_fit/ns.py
qpe_fit/trajectory.py
qpe_fit-0.1.9.dist-info/METADATA
qpe_fit-0.1.9.dist-info/WHEEL
qpe_fit-0.1.9.dist-info/entry_points.txt
qpe_fit-0.1.9.dist-info/top_level.txt
qpe_fit-0.1.9.dist-info/RECORD
