Metadata-Version: 2.4
Name: qpe-fit
Version: 0.1.9
Requires-Dist: numpy
Requires-Dist: ultranest
Requires-Dist: corner
Requires-Dist: matplotlib
Requires-Dist: kerrgeopy
Requires-Dist: h5py
Provides-Extra: gpu
Requires-Dist: cupy-cuda12x; extra == "gpu"
